afmformats/__init__.py
afmformats/_version.py
afmformats/_version_save.py
afmformats/afm_data.py
afmformats/afm_group.py
afmformats/afm_qmap.py
afmformats/afm_segment.py
afmformats/errors.py
afmformats/lazy_loader.py
afmformats/meta.py
afmformats/mod_creep_compliance.py
afmformats/mod_force_distance.py
afmformats/mod_stress_relaxation.py
afmformats/parse_funcs.py
afmformats/formats/__init__.py
afmformats/formats/fmt_hdf5.py
afmformats/formats/fmt_igor.py
afmformats/formats/fmt_ntmdt_txt.py
afmformats/formats/fmt_tab.py
afmformats/formats/fmt_jpk/__init__.py
afmformats/formats/fmt_jpk/jpk_data.py
afmformats/formats/fmt_jpk/jpk_meta.py
afmformats/formats/fmt_jpk/jpk_meta_primary.json
afmformats/formats/fmt_jpk/jpk_meta_secondary.json
afmformats/formats/fmt_jpk/jpk_reader.py
afmformats/formats/fmt_workshop/__init__.py
afmformats/formats/fmt_workshop/ws_map.py
afmformats/formats/fmt_workshop/ws_single.py
afmformats-0.18.4.dist-info/LICENSE
afmformats-0.18.4.dist-info/METADATA
afmformats-0.18.4.dist-info/WHEEL
afmformats-0.18.4.dist-info/top_level.txt
afmformats-0.18.4.dist-info/RECORD
