Metadata-Version: 2.2
Name: afmformats
Version: 0.18.4
Summary: reading common AFM file formats
Home-page: https://github.com/AFM-analysis/afmformats
Author: Paul Müller
Author-email: dev@craban.de
License: MIT
Keywords: atomic force microscopy,mechanical phenotyping,tissue analysis
Platform: ALL
Classifier: Operating System :: OS Independent
Classifier: Programming Language :: Python :: 3
Classifier: Topic :: Scientific/Engineering :: Visualization
Classifier: Intended Audience :: Science/Research
Requires-Python: >=3.6, <4
License-File: LICENSE
Requires-Dist: h5py
Requires-Dist: igor2>=0.5.0
Requires-Dist: jprops
Requires-Dist: numpy>=1.14.0
Dynamic: author
Dynamic: author-email
Dynamic: classifier
Dynamic: description
Dynamic: home-page
Dynamic: keywords
Dynamic: license
Dynamic: platform
Dynamic: requires-dist
Dynamic: requires-python
Dynamic: summary
